Metadata-Version: 1.1
Name: nyc-parking-ticket-checker
Version: 0.0.6
Summary: A module to query for NYC parking tickets
Home-page: https://github.com/fcfort/nyc-parking-ticket-checker
Author: UNKNOWN
Author-email: frank.c.fort@gmail.com
License: UNKNOWN
Keywords: ticket plates violation-number nyc
Platform: UNKNOWN
Classifier: Development Status :: 3 - Alpha
Classifier: License :: OSI Approved :: Apache Software License
Classifier: Programming Language :: Python :: 2
Classifier: Programming Language :: Python :: 2.7
